{
  "version": "7",
  "dialect": "postgresql",
  "entries": [
    {
      "idx": 0,
      "version": "7",
      "when": 1783489828444,
      "tag": "0000_rapid_smiling_tiger",
      "breakpoints": true
    },
    {
      "idx": 1,
      "version": "7",
      "when": 1783516549652,
      "tag": "0001_common_freak",
      "breakpoints": true
    },
    {
      "idx": 2,
      "version": "7",
      "when": 1783518265208,
      "tag": "0002_mean_toro",
      "breakpoints": true
    },
    {
      "idx": 3,
      "version": "7",
      "when": 1783557742341,
      "tag": "0003_misty_george_stacy",
      "breakpoints": true
    },
    {
      "idx": 4,
      "version": "7",
      "when": 1783597728346,
      "tag": "0004_flaky_stephen_strange",
      "breakpoints": true
    },
    {
      "idx": 5,
      "version": "7",
      "when": 1783738792549,
      "tag": "0005_tiny_captain_midlands",
      "breakpoints": true
    },
    {
      "idx": 6,
      "version": "7",
      "when": 1783739199211,
      "tag": "0006_lively_lifeguard",
      "breakpoints": true
    },
    {
      "idx": 7,
      "version": "7",
      "when": 1783824444008,
      "tag": "0007_violet_captain_flint",
      "breakpoints": true
    },
    {
      "idx": 8,
      "version": "7",
      "when": 1784432993332,
      "tag": "0008_nis_opsional",
      "breakpoints": true
    },
    {
      "idx": 9,
      "version": "7",
      "when": 1784866044190,
      "tag": "0009_journal_item_answers",
      "breakpoints": true
    }
  ]
}